cgrr/__init__.py
cgrr/cgrr.py
cgrr/offsets_parser.py
cgrr/parser.py
cgrr/parsetab.py
cgrr-1.3.0.dist-info/METADATA
cgrr-1.3.0.dist-info/RECORD
cgrr-1.3.0.dist-info/WHEEL
cgrr-1.3.0.dist-info/top_level.txt
