Metadata-Version: 2.1
Name: cgrr
Version: 1.3.0
Summary: Classic Game Resource Reader simplifies parsing game resource files
Home-page: https://github.com/sopoforic/cgrr
Author: Tracy Poff
Author-email: tracy.poff@gmail.com
License: UNKNOWN
Platform: UNKNOWN
Classifier: Development Status :: 4 - Beta
Classifier: Topic :: Software Development :: Libraries :: Python Modules
Requires-Dist: ply
